{
  "project_info": {
    "project_number": "288747490447",
    "project_id": "gswebflix",
    "storage_bucket": "gswebflix.appspot.com"
  },
  "client": [
    {
      "client_info": {
        "mobilesdk_app_id": "1:288747490447:android:38fa657d97723d3064f4fa",
        "android_client_info": {
          "package_name": "com.gstech.gswebflix"
        }
      },
      "oauth_client": [
        {
          "client_id": "288747490447-om88t03tqmrvkero5o6qgdq407jf8l8q.apps.googleusercontent.com",
          "client_type": 3
        }
      ],
      "api_key": [
        {
          "current_key": "AIzaSyAbYHIlHhdlaPxzjwkugoXfqkk--H5URJU"
        }
      ],
      "services": {
        "appinvite_service": {
          "other_platform_oauth_client": [
            {
              "client_id": "288747490447-om88t03tqmrvkero5o6qgdq407jf8l8q.apps.googleusercontent.com",
              "client_type": 3
            }
          ]
        }
      }
    }
  ],
  "configuration_version": "1"
}